pyminerva/__init__.py
pyminerva/base.py
pyminerva/finance.py
pyminerva/indices.py
pyminerva/korea.py
pyminerva/krx.py
pyminerva/strategy.py
pyminerva/tech.py
pyminerva/techs.py
pyminerva/data/__init__.py
pyminerva/data/techs_data.py
pyminerva/utils/__init__.py
pyminerva/utils/__settings.py
pyminerva/utils/apis.py
pyminerva/utils/constant.py
pyminerva/utils/extention.py
pyminerva/utils/naverApi.py
pyminerva/utils/rsi.py
pyminerva/utils/settings.py
pyminerva/utils/strategy_funcs.py
pyminerva/utils/tech_funcs.py
tests/__init__.py
tests/test_minerva.py
pyminerva-0.0.448.dist-info/LICENSE
pyminerva-0.0.448.dist-info/METADATA
pyminerva-0.0.448.dist-info/WHEEL
pyminerva-0.0.448.dist-info/top_level.txt
pyminerva-0.0.448.dist-info/RECORD
