Metadata-Version: 2.1
Name: pyminerva
Version: 0.0.448
Summary: To get an insight from Financial Data Anlaysis
Home-page: 
Author: Jeongmin Kang
Author-email: jarvisNim@gmail.com
License: MIT
Project-URL: Bug Reports, https://github.com/jarvisNim/minerva/issues
Project-URL: Source, https://github.com/jarvisNim/minerva
Project-URL: Documentation, https://miraelabs.com/
Keywords: minerva,minerva-api,historical-data,financial-data,stocks,funds,etfs,indices,currency crosses,bonds,commodities,crypto currencies
Classifier: Programming Language :: Python :: 3
Classifier: License :: OSI Approved :: MIT License
Classifier: Operating System :: OS Independent
Requires-Python: >=3.6
License-File: LICENSE
